BA-NSGA/__init__.py
BA-NSGA/main.py
BA-NSGA/convergence/__init__.py
BA-NSGA/convergence/convergence_checker.py
BA-NSGA/io/__init__.py
BA-NSGA/io/io_manager.py
BA-NSGA/mutation_crossover/__init__.py
BA-NSGA/mutation_crossover/crossover.py
BA-NSGA/mutation_crossover/mutation.py
BA-NSGA/mutation_crossover/mutation_crossover_handler.py
BA-NSGA/physical_model/__init__.py
BA-NSGA/physical_model/physical_model.py
bansga/__init__.py
bansga/main.py
bansga/DoE/DoE.py
bansga/DoE/__init__.py
bansga/bayesian_optimization/__init__.py
bansga/bayesian_optimization/bayesian_optimization copy.py
bansga/bayesian_optimization/bayesian_optimization.py
bansga/classification/__init__.py
bansga/classification/clustering.py
bansga/config/__init__.py
bansga/config/params.py
bansga/convergence/__init__.py
bansga/convergence/convergence_checker.py
bansga/explorer/__init__.py
bansga/explorer/explorer.py
bansga/explorer/supercell.py
bansga/io/__init__.py
bansga/io/io_manager.py
bansga/metric/__init__.py
bansga/metric/information_ensemble_metrics.py
bansga/multi_agent_coordinator  /__init__.py
bansga/multi_agent_coordinator  /multi_agent_coordinator.py
bansga/mutation_crossover/__init__.py
bansga/mutation_crossover/crossover.py
bansga/mutation_crossover/mutation.py
bansga/mutation_crossover/mutation_crossover_handler.py
bansga/physical_model/__init__.py
bansga/physical_model/corrections.py
bansga/physical_model/physical_model.py
bansga/selection/__init__.py
bansga/selection/features.py
bansga/selection/multiobjective_selector.py
bansga/selection/objective.py
bansga/selection/ranking.py
bansga/sync/HashBatchSync.py
bansga/sync/__init__.py
bansga/thermostat/__init__.py
bansga/thermostat/thermostat.py
bansga/utils/__init__.py
bansga/utils/canonical_hash.py
bansga/utils/generate_initial_population.py
bansga/utils/helper_functions.py
bansga/utils/lineage.py
bansga/utils/logger.py
bansga/utils/planes.py
bansga/utils/pourbaix_diagram.py
bansga/utils/pourbaix_diagram2.py
BA_NSGA-0.0.4.8.dist-info/METADATA
BA_NSGA-0.0.4.8.dist-info/WHEEL
BA_NSGA-0.0.4.8.dist-info/entry_points.txt
BA_NSGA-0.0.4.8.dist-info/top_level.txt
BA_NSGA-0.0.4.8.dist-info/RECORD
