Metadata-Version: 2.1
Name: BA-NSGA
Version: 0.0.4.8
Summary: A high-dimensional evolutionary structure explorer library
Author: Juan Manuel Lombardi
Author-email: lombardi@fhi-berlin.mpg.de
License: MIT
Keywords: evolutionary optimization high-dimensional structure explorer genetic algorithm
Classifier: Development Status :: 3 - Alpha
Classifier: Intended Audience :: Science/Research
Classifier: Programming Language :: Python :: 3
Classifier: License :: OSI Approved :: MIT License
Classifier: Operating System :: OS Independent
Classifier: Topic :: Scientific/Engineering :: Mathematics
Classifier: Topic :: Scientific/Engineering :: Artificial Intelligence
Requires-Dist: numpy >=1.20
Requires-Dist: matplotlib >=3.4
Requires-Dist: ase >=3.22.1
Requires-Dist: scipy >=1.5
Requires-Dist: scikit-learn >=0.24
Requires-Dist: sage-lib >=0.1.6.3
Requires-Dist: spglib
Requires-Dist: pyyaml
